lupe/__init__.py
lupe/core.py
lupe-0.1.12.dist-info/METADATA
lupe-0.1.12.dist-info/WHEEL
lupe-0.1.12.dist-info/top_level.txt
lupe-0.1.12.dist-info/RECORD
